adlfs/__init__.py
adlfs/_version.py
adlfs/gen1.py
adlfs/spec.py
adlfs/utils.py
adlfs/tests/__init__.py
adlfs/tests/conftest.py
adlfs/tests/test_fetch_range.py
adlfs/tests/test_loop.py
adlfs/tests/test_pickling.py
adlfs/tests/test_spec.py
adlfs/tests/test_uri_format.py
adlfs-2024.7.0.dist-info/LICENSE.txt
adlfs-2024.7.0.dist-info/METADATA
adlfs-2024.7.0.dist-info/WHEEL
adlfs-2024.7.0.dist-info/entry_points.txt
adlfs-2024.7.0.dist-info/top_level.txt
adlfs-2024.7.0.dist-info/RECORD
