Metadata-Version: 2.1
Name: adlfs
Version: 2024.7.0
Summary: Access Azure Datalake Gen1 with fsspec and dask
Maintainer-email: Greg Hayes <hayesgb@gmail.com>
License: BSD
Keywords: file-system,dask,azure
Classifier: Intended Audience :: Developers
Classifier: License :: OSI Approved :: BSD License
Classifier: Operating System :: OS Independent
Classifier: Programming Language :: Python :: 3.8
Classifier: Programming Language :: Python :: 3.9
Classifier: Programming Language :: Python :: 3.10
Requires-Python: >=3.8
License-File: LICENSE.txt
Requires-Dist: azure-core<2.0.0,>=1.23.1
Requires-Dist: azure-datalake-store<0.1,>=0.0.46
Requires-Dist: azure-identity
Requires-Dist: azure-storage-blob>=12.12.0
Requires-Dist: fsspec>=2023.12.0
Requires-Dist: aiohttp>=3.7.0
Provides-Extra: docs
Requires-Dist: sphinx; extra == "docs"
Requires-Dist: myst-parser; extra == "docs"
Requires-Dist: furo; extra == "docs"
Requires-Dist: numpydoc; extra == "docs"
Provides-Extra: tests
Requires-Dist: pytest; extra == "tests"
Requires-Dist: docker; extra == "tests"
Requires-Dist: pytest-mock; extra == "tests"
Requires-Dist: arrow; extra == "tests"
Requires-Dist: dask[dataframe]; extra == "tests"
